[{"subcompanyname":"市发展改革委","p":"100.0"},{"subcompanyname":"市规划资源局","p":"93.3"},{"subcompanyname":"市交通委","p":"91.6"},{"subcompanyname":"市教委","p":"91.6"},{"subcompanyname":"市绿化市容局","p":"86.5"},{"subcompanyname":"市民政局","p":"94.1"},{"subcompanyname":"市农业农村委","p":"92.9"},{"subcompanyname":"市人力资源社会保障局","p":"91.6"},{"subcompanyname":"市水务局","p":"90.6"},{"subcompanyname":"市司法局","p":"91.6"},{"subcompanyname":"市委宣传部","p":"91.6"},{"subcompanyname":"市委政法委","p":"91.6"},{"subcompanyname":"市委组织部","p":"92.1"},{"subcompanyname":"市卫生健康委","p":"91.6"},{"subcompanyname":"市文化旅游局","p":"91.6"},{"subcompanyname":"市住房城乡建设管理委","p":"94.3"}]